test_import_faiss_atran/__init__.py
test_import_faiss_atran/read_data.py
test_import_faiss_atran-0.5.dist-info/METADATA
test_import_faiss_atran-0.5.dist-info/WHEEL
test_import_faiss_atran-0.5.dist-info/top_level.txt
test_import_faiss_atran-0.5.dist-info/RECORD
