Metadata-Version: 2.1
Name: test-import-faiss-atran
Version: 0.5
Summary: Basic Test
Home-page: 
Author: Faisal
Author-email: muhammad.faisal@altran.com
License: UNKNOWN
Platform: UNKNOWN
